_core.cp37-win_amd64.pyd
ivpy/__init__.py
ivpy/core.py
ivpy-0.1.dist-info/LICENSE.txt
ivpy-0.1.dist-info/METADATA
ivpy-0.1.dist-info/WHEEL
ivpy-0.1.dist-info/top_level.txt
ivpy-0.1.dist-info/RECORD
