Metadata-Version: 2.1
Name: ivpy
Version: 0.1
Summary: Discretize continuous arrays using information value.
Home-page: UNKNOWN
Author: Eric E. Graves
Author-email: gravcon5+ivpy@gmail.com
License: LICENSE.txt
Platform: UNKNOWN
